opstrat/__init__.py
opstrat/basic_multi.py
opstrat/basic_single.py
opstrat/blackscholes.py
opstrat/helpers.py
opstrat/tempCodeRunnerFile.py
opstrat/yf.py
opstrat-0.1.7.dist-info/LICENSE
opstrat-0.1.7.dist-info/METADATA
opstrat-0.1.7.dist-info/WHEEL
opstrat-0.1.7.dist-info/top_level.txt
opstrat-0.1.7.dist-info/RECORD
